qase/__init__.py
qase/commons/__init__.py
qase/commons/config.py
qase/commons/loader.py
qase/commons/logger.py
qase/commons/utils.py
qase/commons/client/api_v1_client.py
qase/commons/client/api_v2_client.py
qase/commons/client/base_api_client.py
qase/commons/exceptions/reporter.py
qase/commons/models/__init__.py
qase/commons/models/attachment.py
qase/commons/models/basemodel.py
qase/commons/models/external_link.py
qase/commons/models/relation.py
qase/commons/models/result.py
qase/commons/models/run.py
qase/commons/models/runtime.py
qase/commons/models/step.py
qase/commons/models/config/api.py
qase/commons/models/config/batch.py
qase/commons/models/config/connection.py
qase/commons/models/config/framework.py
qase/commons/models/config/plan.py
qase/commons/models/config/qaseconfig.py
qase/commons/models/config/report.py
qase/commons/models/config/run.py
qase/commons/models/config/testops.py
qase/commons/profilers/__init__.py
qase/commons/profilers/db.py
qase/commons/profilers/network.py
qase/commons/profilers/sleep.py
qase/commons/reporters/__init__.py
qase/commons/reporters/core.py
qase/commons/reporters/report.py
qase/commons/reporters/testops.py
qase/commons/status_mapping/__init__.py
qase/commons/status_mapping/status_mapping.py
qase/commons/util/__init__.py
qase/commons/util/host_data.py
qase/commons/validators/base.py
qase_python_commons-4.1.10.dist-info/METADATA
qase_python_commons-4.1.10.dist-info/WHEEL
qase_python_commons-4.1.10.dist-info/top_level.txt
qase_python_commons-4.1.10.dist-info/RECORD
