Metadata-Version: 2.4
Name: qase-python-commons
Version: 4.1.10
Summary: A library for Qase TestOps and Qase Report
Author-email: Qase Team <support@qase.io>
Project-URL: Homepage, https://github.com/qase-tms/qase-python/tree/main/qase-python-commons
Classifier: Development Status :: 5 - Production/Stable
Classifier: Programming Language :: Python
Classifier: Intended Audience :: Developers
Classifier: License :: OSI Approved :: Apache Software License
Classifier: Topic :: Software Development :: Quality Assurance
Classifier: Topic :: Software Development :: Testing
Classifier: Programming Language :: Python :: 3
Classifier: Programming Language :: Python :: 3 :: Only
Classifier: Programming Language :: Python :: 3.9
Classifier: Programming Language :: Python :: 3.10
Classifier: Programming Language :: Python :: 3.11
Classifier: Programming Language :: Python :: 3.12
Classifier: Programming Language :: Python :: 3.13
Requires-Python: >=3.9
Requires-Dist: certifi>=2024.2.2
Requires-Dist: attrs>=23.2.0
Requires-Dist: qase-api-client~=2.0.3
Requires-Dist: qase-api-v2-client~=2.0.3
Requires-Dist: more_itertools
Provides-Extra: testing
Requires-Dist: pytest; extra == "testing"
Requires-Dist: pytest-cov; extra == "testing"
Requires-Dist: mock; extra == "testing"
Requires-Dist: more_itertools; extra == "testing"
Requires-Dist: requests; extra == "testing"
Requires-Dist: urllib3; extra == "testing"
Requires-Dist: freezegun; extra == "testing"
